pyconcordion2/__init__.py
pyconcordion2/base.py
pyconcordion2/commands.py
pyconcordion2/expression_parser.py
pyconcordion2/resources/embedded.css
pyconcordion2/resources/main.js
pyconcordion2/tests/__init__.py
pyconcordion2/tests/test_rig.py
pyconcordion2/tests/spec/IndexTest.py
pyconcordion2/tests/spec/__init__.py
pyconcordion2/tests/spec/run_test.py
pyconcordion2/tests/spec/concordion/ConcordionTest.py
pyconcordion2/tests/spec/concordion/ExampleTest.py
pyconcordion2/tests/spec/concordion/__init__.py
pyconcordion2/tests/spec/concordion/command/CommandTest.py
pyconcordion2/tests/spec/concordion/command/__init__.py
pyconcordion2/tests/spec/concordion/command/assertEquals/AssertEqualsTest.py
pyconcordion2/tests/spec/concordion/command/assertEquals/ExceptionsTest.py
pyconcordion2/tests/spec/concordion/command/assertEquals/NestedActionsTest.py
pyconcordion2/tests/spec/concordion/command/assertEquals/NestedElementsTest.py
pyconcordion2/tests/spec/concordion/command/assertEquals/SupportedElementsTest.py
pyconcordion2/tests/spec/concordion/command/assertEquals/__init__.py
pyconcordion2/tests/spec/concordion/command/assertEquals/nonString/NonStringTest.py
pyconcordion2/tests/spec/concordion/command/assertEquals/nonString/NullResultTest.py
pyconcordion2/tests/spec/concordion/command/assertEquals/nonString/VoidResultTest.py
pyconcordion2/tests/spec/concordion/command/assertEquals/nonString/__init__.py
pyconcordion2/tests/spec/concordion/command/assertEquals/whitespace/LineContinuationsTest.py
pyconcordion2/tests/spec/concordion/command/assertEquals/whitespace/NormalizationTest.py
pyconcordion2/tests/spec/concordion/command/assertEquals/whitespace/WhitespaceTest.py
pyconcordion2/tests/spec/concordion/command/assertEquals/whitespace/__init__.py
pyconcordion2/tests/spec/concordion/command/assertFalse/AssertFalseTest.py
pyconcordion2/tests/spec/concordion/command/assertFalse/__init__.py
pyconcordion2/tests/spec/concordion/command/assertTrue/AssertTrueTest.py
pyconcordion2-0.15.1.dist-info/METADATA
pyconcordion2-0.15.1.dist-info/WHEEL
pyconcordion2-0.15.1.dist-info/entry_points.txt
pyconcordion2-0.15.1.dist-info/top_level.txt
pyconcordion2-0.15.1.dist-info/RECORD
