Metadata-Version: 2.1
Name: pyconcordion2
Version: 0.15.1
Summary: Concordion Python Port
Home-page: https://github.com/concordion/pyconcordion2
Author: John Jiang
Author-email: johnjiang101@gmail.com
License: Apache Software License
Keywords: concordion acceptance-test
Platform: UNKNOWN
Classifier: Topic :: Software Development :: Testing
Classifier: License :: OSI Approved :: Apache Software License
Requires-Dist: enum34
Requires-Dist: mock
Requires-Dist: lxml
Requires-Dist: pyparsing
